ALU.v
`define AND   4'b0000
`define OR    4'b0001
`define ADD   4'b0010
`define SUB   4'b0110
`define PassB 4'b0111


module ALU(BusW, BusA, BusB, ALUCtrl, Zero);
    
    parameter n = 64;

    output  [n-1:0] BusW;
    input   [n-1:0] BusA, BusB;
    input   [3:0] ALUCtrl;
    output  Zero;
    
    reg     [n-1:0] BusW;
    
    always @(ALUCtrl or BusA or BusB) begin
        case(ALUCtrl)
            `AND: begin
                BusW = BusA & BusB; //And operation when Ctrl == 0000
            end
            `OR: begin
                BusW = BusA | BusB; //Or operation when Ctrl == 00001
            end
            `ADD: begin
                BusW = BusA + BusB; //Add operation when Ctrl == 0010
            end
            `SUB: begin
                BusW = BusA - BusB; //Sub operation when Ctrl == 0110
            end
            `PassB: begin
                BusW = BusB; //PassB operation when Ctrl == 0111
            end
        endcase
    end

    assign Zero = (BusW == 0) ? 1 : 0; //If BusW is Zero, then the Zero bit will be 1
    
endmodule

ALUTest.v
`timescale 1ns / 1ps

////////////////////////////////////////////////////////////////////////////////
// Company: 
// Engineer:
//
// Create Date:   10:02:47 03/05/2009
// Design Name:   ALU
// Module Name:   E:/350/Lab8/ALU/ALUTest.v
// Project Name:  ALU
// Target Device:  
// Tool versions:  
// Description: 
//
// Verilog Test Fixture created by ISE for module: ALU
//
// Dependencies:
// 
// Revision:
// Revision 0.01 - File Created
// Additional Comments:
// 
////////////////////////////////////////////////////////////////////////////////

`define STRLEN 32
module ALUTest_v;

  initial
    begin
      $dumpfile("ALUTest.vcd");
      $dumpvars(0,ALUTest_v);
    end


	task passTest;
		input [64:0] actualOut, expectedOut;
		input [`STRLEN*8:0] testType;
		inout [7:0] passed;
	
		if(actualOut == expectedOut) begin $display ("%s passed", testType); passed = passed + 1; end
		else $display ("%s failed: %x should be %x", testType, actualOut, expectedOut);
	endtask
	
	task allPassed;
		input [7:0] passed;
		input [7:0] numTests;
		
		if(passed == numTests) $display ("All tests passed");
		else $display("Some tests failed");
	endtask

	// Inputs
	reg [63:0] BusA;
	reg [63:0] BusB;
	reg [3:0] ALUCtrl;
	reg [7:0] passed;

	// Outputs
	wire [63:0] BusW;
	wire Zero;

	// Instantiate the Unit Under Test (UUT)
	ALU uut (
		.BusW(BusW), 
		.Zero(Zero), 
		.BusA(BusA), 
		.BusB(BusB), 
		.ALUCtrl(ALUCtrl)
	);

	initial begin
		// Initialize Inputs
		BusA = 0;
		BusB = 0;
		ALUCtrl = 0;
		passed = 0;

     // Here is one example test vector, testing the ADD instruction:
                
		{BusA, BusB, ALUCtrl} = {64'h1234, 64'hABCD0000, 4'h2}; #40; passTest({Zero, BusW}, 65'h0ABCD1234, "ADD 0x1234,0xABCD0000", passed);
   
		//Reformate and add your test vectors from the prelab here following the example of the testvector above.	
   
  	{BusA, BusB, ALUCtrl} = {64'h0, 64'h0, 4'h0}; #40; passTest({Zero, BusW}, {1'b1, 64'h000000000000000}, "AND1", passed); // 0x0 AND1 0x0
		{BusA, BusB, ALUCtrl} = {64'h20, 64'h20, 4'h0}; #40; passTest({Zero, BusW}, 65'h0000000000000020, "AND2", passed); // 0x20 AND2 0x20
		{BusA, BusB, ALUCtrl} = {64'h100, 64'h20, 4'h0}; #40; passTest({Zero, BusW}, {1'b1, 64'h000000000000000}, "AND3", passed); //0x100 AND3 0x20

		{BusA, BusB, ALUCtrl} = {64'h1, 64'h0, 4'h1}; #40; passTest({Zero, BusW}, 65'h0000000000000001, "ORR1", passed); // 0x1 ORR1 0x0
		{BusA, BusB, ALUCtrl} = {64'h11, 64'h10, 4'h1}; #40; passTest({Zero, BusW}, 65'h0000000000000011, "ORR2", passed); // 0x11 ORR2 0x10
		{BusA, BusB, ALUCtrl} = {64'h35, 64'h25, 4'h1}; #40; passTest({Zero, BusW}, 65'h0000000000000035, "ORR3", passed); // 0x35 ORR3 0x25

		{BusA, BusB, ALUCtrl} = {64'h20, 64'h4501, 4'h2}; #40; passTest({Zero, BusW}, 65'h0000000000004521, "ADD1", passed); // 0x20 ADD1 0x4501
		{BusA, BusB, ALUCtrl} = {64'h0, 64'h1, 4'h2}; #40; passTest({Zero, BusW}, 65'h0000000000000001, "ADD2", passed); // 0x0 ADD2 0x1
		{BusA, BusB, ALUCtrl} = {64'h10, 64'h10, 4'h2}; #40; passTest({Zero, BusW}, 65'h0000000000000020, "ADD3", passed); // 0x10 ADD3 0x10

		{BusA, BusB, ALUCtrl} = {64'h10, 64'h10, 4'h6}; #40; passTest({Zero, BusW}, {1'b1, 64'h000000000000000}, "SUB1", passed); // 0x10 SUB1 0x10
		{BusA, BusB, ALUCtrl} = {64'h90, 64'h10, 4'h6}; #40; passTest({Zero, BusW}, 65'h0000000000000080, "SUB2", passed); // 0x90 SUB2 0x10
		{BusA, BusB, ALUCtrl} = {64'h80, 64'h20, 4'h6}; #40; passTest({Zero, BusW}, 65'h000000000000060, "SUB3", passed); // 0x80 SUB3 0x20

		{BusA, BusB, ALUCtrl} = {64'h4, 64'h1, 4'h7}; #40; passTest({Zero, BusW}, 65'h0000000000000001, "PassB1", passed); // 0x4, 0x1 PassB1
		{BusA, BusB, ALUCtrl} = {64'h3, 64'h10, 4'h7}; #40; passTest({Zero, BusW}, 65'h0000000000000010, "PassB2", passed); // 0x3, 0x10 PassB2
		{BusA, BusB, ALUCtrl} = {64'h2, 64'h15, 4'h7}; #40; passTest({Zero, BusW}, 65'h0000000000000015, "PassB3", passed); // 0x2, 0x15 PassB3
		#10;
   
		allPassed(passed, 16);  //check to see if all tests are passed
   
	end
      
endmodule

ALUTest.vcd
$date
	Tue Jun 11 10:25:15 2024
$end
$version
	Icarus Verilog
$end
$timescale
	1ps
$end
$scope module ALUTest_v $end
$var wire 1 ! Zero $end
$var wire 64 " BusW [63:0] $end
$var reg 4 # ALUCtrl [3:0] $end
$var reg 64 $ BusA [63:0] $end
$var reg 64 % BusB [63:0] $end
$var reg 8 & passed [7:0] $end
$scope module uut $end
$var wire 4 ' ALUCtrl [3:0] $end
$var wire 64 ( BusA [63:0] $end
$var wire 64 ) BusB [63:0] $end
$var wire 1 ! Zero $end
$var reg 64 * BusW [63:0] $end
$upscope $end
$scope task allPassed $end
$var reg 8 + numTests [7:0] $end
$var reg 8 , passed [7:0] $end
$upscope $end
$scope task passTest $end
$var reg 65 - actualOut [64:0] $end
$var reg 65 . expectedOut [64:0] $end
$var reg 8 / passed [7:0] $end
$var reg 257 0 testType [256:0] $end
$upscope $end
$upscope $end
$enddefinitions $end
#0
$dumpvars
bx 0
bx /
bx .
bx -
bx ,
bx +
b10101011110011010001001000110100 *
b10101011110011010000000000000000 )
b1001000110100 (
b10 '
b0 &
b10101011110011010000000000000000 %
b1001000110100 $
b10 #
b10101011110011010001001000110100 "
0!
$end
#40000
1!
b0 "
b0 *
b0 $
b0 (
b0 %
b0 )
b0 #
b0 '
b1 &
b1 /
b10000010100010001000100001000000011000001111000001100010011001000110011001101000010110000110000011110000100000101000010010000110100010000110000001100000011000000110000 0
b10101011110011010001001000110100 .
b10101011110011010001001000110100 -
#80000
0!
b100000 "
b100000 *
b100000 $
b100000 (
b100000 %
b100000 )
b10 &
b10 /
b1000001010011100100010000110001 0
b10000000000000000000000000000000000000000000000000000000000000000 .
b10000000000000000000000000000000000000000000000000000000000000000 -
#120000
1!
b0 "
b0 *
b100000000 $
b100000000 (
b11 &
b11 /
b1000001010011100100010000110010 0
b100000 .
b100000 -
#160000
0!
b1 "
b1 *
b1 $
b1 (
b0 %
b0 )
b1 #
b1 '
b100 &
b100 /
b1000001010011100100010000110011 0
b10000000000000000000000000000000000000000000000000000000000000000 .
b10000000000000000000000000000000000000000000000000000000000000000 -
#200000
b10001 "
b10001 *
b10001 $
b10001 (
b10000 %
b10000 )
b101 &
b101 /
b1001111010100100101001000110001 0
b1 .
b1 -
#240000
b110101 "
b110101 *
b110101 $
b110101 (
b100101 %
b100101 )
b110 &
b110 /
b1001111010100100101001000110010 0
b10001 .
b10001 -
#280000
b100010100100001 "
b100010100100001 *
b100000 $
b100000 (
b100010100000001 %
b100010100000001 )
b10 #
b10 '
b111 &
b111 /
b1001111010100100101001000110011 0
b110101 .
b110101 -
#320000
b1 "
b1 *
b0 $
b0 (
b1 %
b1 )
b1000 &
b1000 /
b1000001010001000100010000110001 0
b100010100100001 .
b100010100100001 -
#360000
b100000 "
b100000 *
b10000 $
b10000 (
b10000 %
b10000 )
b1001 &
b1001 /
b1000001010001000100010000110010 0
b1 .
b1 -
#400000
1!
b0 "
b0 *
b110 #
b110 '
b1010 &
b1010 /
b1000001010001000100010000110011 0
b100000 .
b100000 -
#440000
0!
b10000000 "
b10000000 *
b10010000 $
b10010000 (
b1011 &
b1011 /
b1010011010101010100001000110001 0
b10000000000000000000000000000000000000000000000000000000000000000 .
b10000000000000000000000000000000000000000000000000000000000000000 -
#480000
b1100000 "
b1100000 *
b10000000 $
b10000000 (
b100000 %
b100000 )
b1100 &
b1100 /
b1010011010101010100001000110010 0
b10000000 .
b10000000 -
#520000
b1 "
b1 *
b100 $
b100 (
b1 %
b1 )
b111 #
b111 '
b1101 &
b1101 /
b1010011010101010100001000110011 0
b1100000 .
b1100000 -
#560000
b10000 "
b10000 *
b11 $
b11 (
b10000 %
b10000 )
b1110 &
b1110 /
b10100000110000101110011011100110100001000110001 0
b1 .
b1 -
#600000
b10101 "
b10101 *
b10 $
b10 (
b10101 %
b10101 )
b1111 &
b1111 /
b10100000110000101110011011100110100001000110010 0
b10000 .
b10000 -
#640000
b10000 &
b10000 /
b10100000110000101110011011100110100001000110011 0
b10101 .
b10101 -
#650000
b10000 +
b10000 ,
